<?xml version="1.0" encoding="utf-8"?>
<!DOCTYPE hibernate-mapping PUBLIC "-//Hibernate/Hibernate Mapping DTD 3.0//EN"
"http://hibernate.sourceforge.net/hibernate-mapping-3.0.dtd">
<!-- 
    Mapping file autogenerated by MyEclipse Persistence Tools
-->
<hibernate-mapping>
    <class name="com.by.hctm.system.entity.TSysUserInoutLog" table="T_SYS_USER_INOUT_LOG" >
        <id name="uilId" type="java.lang.Long">
            <column name="UIL_ID" precision="10" scale="0" />
            <generator class="sequence" >
            <param name="sequence">SEQ_USER_INOUT_LOG_ID</param>
            </generator>
        </id>
        <property name="userLoginName" type="java.lang.String">
            <column name="USER_LOGIN_NAME" length="50" />
        </property>
        <property name="userChineseName" type="java.lang.String">
            <column name="USER_CHINESE_NAME" length="50" />
        </property>
        <property name="ipAddress" type="java.lang.String">
            <column name="IP_ADDRESS" length="20" />
        </property>
        <property name="loginDate" type="java.util.Date">
            <column name="LOGIN_DATE" />
        </property>
        <property name="logoutDate" type="java.util.Date">
            <column name="LOGOUT_DATE" />
        </property>
        <property name="sessionPath" type="java.lang.String">
            <column name="SESSION_PATH" length="300" />
        </property>
        <property name="lineStatus" type="java.lang.String">
            <column name="LINE_STATUS" length="1" />
        </property>
        <property name="remark" type="java.lang.String">
            <column name="REMARK" length="100" />
        </property>
    </class>
</hibernate-mapping>
